pybalu/__init__.py
pybalu/base.py
pybalu/classification/__init__.py
pybalu/classification/structure.py
pybalu/misc/__init__.py
pybalu/feature_analysis/sp100.py
pybalu/feature_analysis/__init__.py
pybalu/feature_analysis/jfisher.py
pybalu/feature_analysis/score.py
pybalu/feature_extraction/flusser.py
pybalu/feature_extraction/gupta.py
pybalu/feature_extraction/hugeo.py
pybalu/feature_extraction/hog_utils.c
pybalu/feature_extraction/haralick_utils.cpython-312-darwin.so
pybalu/feature_extraction/basic_geo.py
pybalu/feature_extraction/haralick_utils.c
pybalu/feature_extraction/flusser_utils.cpython-312-darwin.so
pybalu/feature_extraction/__init__.py
pybalu/feature_extraction/flusser_utils.c
pybalu/feature_extraction/gabor.py
pybalu/feature_extraction/all.py
pybalu/feature_extraction/hog_utils.cpython-312-darwin.so
pybalu/feature_extraction/hog.py
pybalu/feature_extraction/basic_int.py
pybalu/feature_extraction/lbp.py
pybalu/feature_extraction/fourier_des.py
pybalu/feature_extraction/geometric_utils.c
pybalu/feature_extraction/haralick.py
pybalu/feature_extraction/from_image_set.py
pybalu/feature_extraction/fourier.py
pybalu/feature_extraction/huint.py
pybalu/feature_extraction/geometric_utils.cpython-312-darwin.so
pybalu/data_selection/__init__.py
pybalu/data_selection/stratify.py
pybalu/io/__init__.py
pybalu/io/image_set.py
pybalu/io/print_features.py
pybalu/io/imread.py
pybalu/feature_selection/clean.py
pybalu/feature_selection/exsearch.py
pybalu/feature_selection/sfs.py
pybalu/feature_selection/__init__.py
pybalu/performance_eval/crossval.py
pybalu/performance_eval/__init__.py
pybalu/performance_eval/performance.py
pybalu/performance_eval/confusion.py
pybalu/img_processing/fst_deriv.py
pybalu/img_processing/__init__.py
pybalu/img_processing/rgb2hcm.py
pybalu/img_processing/segbalu.py
pybalu/img_processing/morphoreg.py
pybalu/img_processing/snd_deriv.py
pybalu/feature_transformation/normalize.py
pybalu-0.3.1.dist-info/RECORD
pybalu-0.3.1.dist-info/LICENSE
pybalu-0.3.1.dist-info/WHEEL
pybalu-0.3.1.dist-info/top_level.txt
pybalu-0.3.1.dist-info/METADATA
