Metadata-Version: 2.1
Name: pybalu
Version: 0.3.1
Summary: Python3 implementation of the computer vision and pattern recognition library Balu.
Author-email: Domingo Mery <domingo.mery@uc.cl>, Marco Bucchi <mabucchi@uc.cl>
Maintainer-email: Christian Pieringer <cppierin@uc.cl>
License:                     GNU GENERAL PUBLIC LICENSE
Requires-Python: >=3.10
License-File: LICENSE
Requires-Dist: numpy>=1.21.0
Requires-Dist: scipy
Requires-Dist: Pillow
Requires-Dist: imageio
Requires-Dist: scikit-learn
Requires-Dist: scikit-image
Requires-Dist: tqdm
Provides-Extra: dev
Requires-Dist: black; extra == "dev"
Requires-Dist: flake8; extra == "dev"
Requires-Dist: ruff; extra == "dev"
Requires-Dist: matplotlib; extra == "dev"
